ims/fieldupdater/__init__.py
ims/fieldupdater/configure.zcml
ims/fieldupdater/testing.py
ims/fieldupdater/browser/__init__.py
ims/fieldupdater/browser/configure.zcml
ims/fieldupdater/browser/mass.pt
ims/fieldupdater/browser/mass.py
ims/fieldupdater/browser/schema.pt
ims/fieldupdater/profiles/default/controlpanel.xml
ims/fieldupdater/profiles/default/metadata.xml
ims/fieldupdater/profiles/uninstall/controlpanel.xml
ims.fieldupdater-3.0.1.dist-info/METADATA
ims.fieldupdater-3.0.1.dist-info/WHEEL
ims.fieldupdater-3.0.1.dist-info/entry_points.txt
ims.fieldupdater-3.0.1.dist-info/RECORD
